pfund_plugins/base_plugin.py
pfund_plugins/llm_plugin.py
pfund_plugins-0.0.1.dev1.dist-info/LICENSE
pfund_plugins-0.0.1.dev1.dist-info/METADATA
pfund_plugins-0.0.1.dev1.dist-info/WHEEL
pfund_plugins-0.0.1.dev1.dist-info/RECORD
